potemkeys/__init__.py
potemkeys/__main__.py
potemkeys/Config.py
potemkeys/GlobalState.py
potemkeys/KeyEventUtils.py
potemkeys/pelleds.jpg
potemkeys/potemkeysoptions.jsonc
potemkeys/tests/__init__.py
potemkeys/tests/test_potato.py
potemkeys/Utils.py
potemkeys-1.0.3.dist-info/LICENSE
potemkeys-1.0.3.dist-info/WHEEL
potemkeys-1.0.3.dist-info/METADATA
potemkeys-1.0.3.dist-info/RECORD
