Metadata-Version: 2.1
Name: potemkeys
Version: 1.0.3
Summary: Fighting games for goldfish with keyboards >:3c
Home-page: https://github.com/henryfbp/potemkeys
Keywords: pygame,fighting-game,tekken,guilty-gear-strive
Author: henryfbp
Author-email: HenryFBP@gmail.com
Requires-Python: >=3.6,<4.0
Classifier: Programming Language :: Python :: 3
Classifier: Programming Language :: Python :: 3.10
Classifier: Programming Language :: Python :: 3.6
Classifier: Programming Language :: Python :: 3.7
Classifier: Programming Language :: Python :: 3.8
Classifier: Programming Language :: Python :: 3.9
Requires-Dist: json5 (>=0.9.6,<0.10.0)
Requires-Dist: mergedeep (>=1.3.4,<2.0.0)
Requires-Dist: pygame (>=2.1.2,<3.0.0)
Requires-Dist: pynput (>=1.7.6,<2.0.0)
Requires-Dist: python3-xlib; sys_platform != "win32"
Requires-Dist: pywin32-ctypes; sys_platform == "win32"
